exploit/Exploit.py
exploit/__init__.py
exploit/blueborne.py
exploit/BlueBorne/CVE20170781.py
exploit/BlueBorne/CVE20170785.py
exploit/BlueBorne/__init__.py
pybt/__init__.py
pybt/bt.py
pybt/libs/Device.py
pybt/libs/Service.py
pybt/libs/Static.py
pybt/libs/__init__.py
pybt/libs/bt/__init__.py
pybt/libs/bt/beacon.py
pybt/libs/bt/classic.py
pybt/libs/bt/le.py
pybt_smthnspcl-0.43.dist-info/METADATA
pybt_smthnspcl-0.43.dist-info/WHEEL
pybt_smthnspcl-0.43.dist-info/top_level.txt
pybt_smthnspcl-0.43.dist-info/RECORD
