Metadata-Version: 2.1
Name: pybt-smthnspcl
Version: 0.43
Summary: bluetooth library
Home-page: https://github.com/smthnspcl/pybt
Author: Pascal Eberlein
Author-email: pascal@eberlein.io
License: UNKNOWN
Keywords: bluetooth library
Platform: UNKNOWN
Classifier: Development Status :: 3 - Alpha
Classifier: Intended Audience :: Developers
Classifier: Topic :: Software Development :: Build Tools
Classifier: License :: OSI Approved :: MIT License
Classifier: Programming Language :: Python :: 3.6
